sample/__init__.py
dfmodule_sg-0.0.2.dist-info/METADATA
dfmodule_sg-0.0.2.dist-info/WHEEL
dfmodule_sg-0.0.2.dist-info/top_level.txt
dfmodule_sg-0.0.2.dist-info/RECORD
