Metadata-Version: 2.1
Name: dfmodule-sg
Version: 0.0.2
Summary: A simple dfmodule_sg example package
Home-page: http://github.com/yourusername/sample_package
Author: ente
Author-email: your.email@example.com
Keywords: dfmodule_sg,dfmodule
Classifier: Programming Language :: Python :: 3.6
Classifier: Programming Language :: Python :: 3.7
Classifier: Programming Language :: Python :: 3.8
Classifier: Programming Language :: Python :: 3.9
Classifier: Programming Language :: Python :: 3.10
Requires-Python: >=3.6
Requires-Dist: pandas
Requires-Dist: numpy
